LICENSE.txt
MANIFEST.in
README.md
setup.py
bin/ipa-dump-info
bin/ipa-unzip-bin
ipa/__init__.py
libipa.egg-info/PKG-INFO
libipa.egg-info/SOURCES.txt
libipa.egg-info/dependency_links.txt
libipa.egg-info/requires.txt
libipa.egg-info/top_level.txt