Metadata-Version: 1.0
Name: libipa
Version: 0.0.6
Summary: Library to read IPA files (iOS application archives).
Home-page: https://github.com/Tatsh/libipa
Author: Andrew Udvare
Author-email: audvare@gmail.com
License: LICENSE.txt
Platform: UNKNOWN
